pychilaslasers/__init__.py
pychilaslasers/calibration/__init__.py
pychilaslasers/calibration/calibration_parsing.py
pychilaslasers/calibration/defaults.py
pychilaslasers/calibration/structs.py
pychilaslasers/comm.py
pychilaslasers/constants.py
pychilaslasers/exceptions/__init__.py
pychilaslasers/exceptions/calibration_error.py
pychilaslasers/exceptions/laser_error.py
pychilaslasers/exceptions/mode_error.py
pychilaslasers/laser.py
pychilaslasers/laser_components/__init__.py
pychilaslasers/laser_components/diode.py
pychilaslasers/laser_components/heaters/__init__.py
pychilaslasers/laser_components/heaters/heater_channels.py
pychilaslasers/laser_components/heaters/heaters.py
pychilaslasers/laser_components/laser_component.py
pychilaslasers/laser_components/tec.py
pychilaslasers/modes/__init__.py
pychilaslasers/modes/calibrated.py
pychilaslasers/modes/manual_mode.py
pychilaslasers/modes/mode.py
pychilaslasers/modes/sweep_mode.py
pychilaslasers/modes/tune_mode.py
pychilaslasers-1.0.14.dist-info/WHEEL
pychilaslasers-1.0.14.dist-info/METADATA
pychilaslasers-1.0.14.dist-info/RECORD
