Metadata-Version: 2.4
Name: pychilaslasers
Version: 1.0.14
Summary: Python library for controlling Chilas lasers
Author: Chilas B.V.
Author-email: Chilas B.V. <software@chilas.com>
License-Expression: Apache-2.0
Requires-Dist: pyserial>=3.5
Requires-Python: >=3.10
